{
  "parts": [
    {
      "implements": "part:@sanity/base/tool",
      "path": "tool.js"
    },
    {
      "implements": "part:@sanity/base/document-actions/resolver",
      "path": "documentActions.js"
    },
    {
      "implements": "part:@sanity/base/document-badges/resolver",
      "path": "documentBadges.js"
    },
    {
      "implements": "part:@sanity/form-builder/input-resolver",
      "path": "inputResolver.js"
    }
  ],
  "paths": {
    "source": "./src",
    "compiled": "./lib"
  }
}
